LICENSE
MANIFEST.in
README.md
setup.cfg
setup.py
pickle_mixin/__init__.py
pickle_mixin/_core.py
pickle_mixin.egg-info/PKG-INFO
pickle_mixin.egg-info/SOURCES.txt
pickle_mixin.egg-info/dependency_links.txt
pickle_mixin.egg-info/top_level.txt
pickle_mixin.egg-info/zip-safe
pickle_mixin/test/test_pickle_by_name.py
pickle_mixin/test/test_pickle_mixin.py