Metadata-Version: 1.1
Name: pickle-mixin
Version: 1.0.1
Summary: Makes un-pickle-able objects pick-able.
Home-page: https://github.com/limix/pickle-mixin
Author: Danilo Horta
Author-email: horta@ebi.ac.uk
License: MIT
Platform: UNKNOWN
Classifier: Development Status :: 5 - Production/Stable
Classifier: License :: OSI Approved :: MIT License
Classifier: Operating System :: OS Independent
